{
  "updated_at": "2026-07-23T17:39:46.698709+00:00",
  "items": [
    {
      "title": "Liverpool latest: Goalkeeper signs new deal as another leaves on loan",
      "title_cn": "",
      "url": "https://www.skysports.com/football/live-blog/12040/13025501/liverpool-transfer-news-rumours-and-gossip-live-updates-and-latest-on-deals-signings-loans-and-contracts",
      "source": "Sky Sports",
      "tier": 2,
      "published": "2026-07-23T16:23:00+00:00",
      "score": 33.0,
      "keywords": [
        "Liverpool",
        "latest",
        "Goalkeeper",
        "signs",
        "deal",
        "another"
      ],
      "summary": "",
      "summary_cn": ""
    },
    {
      "title": "Man United ticket deals for 2026/27 Premier League season games at Old Trafford plus hotels and VIP hospitality",
      "title_cn": "",
      "url": "https://www.thesun.co.uk/sport/39220790/man-united-premier-league-ticket-hotel-packages/",
      "source": "The Sun",
      "tier": 2,
      "published": "2026-07-23T15:41:39+00:00",
      "score": 33.0,
      "keywords": [
        "Manchester United",
        "Man United",
        "Man Utd",
        "United",
        "ticket",
        "deals"
      ],
      "summary": "MANCHESTER United fans have every reason to be excited for the new 2026/27 Premier League season at Old Trafford. The official Premier League fixtures are out – and we have the ultimate way to guarantee your place at the Theatre of Dreams. Man Utd ticket deals Old Trafford is always sold out but Uni",
      "summary_cn": ""
    },
    {
      "title": "'Kings of Manchester' - Anderson sends Man Utd message after City move sealed",
      "title_cn": "",
      "url": "https://www.skysports.com/football/news/12040/13566398/elliot-anderson-new-man-city-signing-sends-man-utd-message-after-completing-116m-move-from-nottingham-forest",
      "source": "Sky Sports",
      "tier": 2,
      "published": "2026-07-23T17:30:00+00:00",
      "score": 31.0,
      "keywords": [
        "Manchester City",
        "Nottingham Forest",
        "Man Utd",
        "Forest",
        "Anderson",
        "Kings"
      ],
      "summary": "Elliot Anderson has declared Manchester City the \"kings of Manchester\" after completing his &#163;116m move from Nottingham Forest.",
      "summary_cn": ""
    },
    {
      "title": "Rodri to undergo back surgery and may miss start of Premier League season",
      "title_cn": "",
      "url": "https://www.skysports.com/football/news/12040/13566264/rodri-man-citys-world-cup-winner-to-undergo-back-surgery-and-may-miss-start-of-premier-league-season",
      "source": "Sky Sports",
      "tier": 2,
      "published": "2026-07-23T16:40:00+00:00",
      "score": 31.0,
      "keywords": [
        "Manchester City",
        "Rodri",
        "undergo",
        "back",
        "surgery",
        "miss"
      ],
      "summary": "Manchester City's World Cup winner Rodri is to undergo minor surgery on his back, which means he may miss the start of the Premier League season.",
      "summary_cn": ""
    },
    {
      "title": "Anderson's journey to England star and Man City record signing",
      "title_cn": "",
      "url": "https://www.bbc.co.uk/sport/football/articles/c1eyjvzeg8qo?at_medium=RSS&at_campaign=rss",
      "source": "BBC Sport",
      "tier": 2,
      "published": "2026-07-23T17:16:34+00:00",
      "score": 31.0,
      "keywords": [
        "Manchester City",
        "Man City",
        "Anderson",
        "journey",
        "England",
        "star"
      ],
      "summary": "Elliot Anderson was a key part of England's World Cup side and is now Manchester City's record signing.",
      "summary_cn": ""
    },
    {
      "title": "Anderson gets Man City move he craved as £116m deal done",
      "title_cn": "",
      "url": "https://www.bbc.co.uk/sport/football/articles/c1j1gk23jj4o?at_medium=RSS&at_campaign=rss",
      "source": "BBC Sport",
      "tier": 2,
      "published": "2026-07-23T16:01:00+00:00",
      "score": 31.0,
      "keywords": [
        "Manchester City",
        "Man City",
        "Anderson",
        "gets",
        "City",
        "move"
      ],
      "summary": "Manchester City confirm the arrival of Elliot Anderson on a five-year deal, as the England player is tipped to become a \"complete midfielder\" at his new club.",
      "summary_cn": ""
    },
    {
      "title": "Elliot Anderson lauds City as ‘kings of Manchester’ after £116m Forest transfer",
      "title_cn": "",
      "url": "https://www.theguardian.com/football/2026/jul/23/elliot-anderson-manchester-city-116m-nottingham-forest-transfer-premier-league",
      "source": "The Guardian",
      "tier": 2,
      "published": "2026-07-23T16:00:48+00:00",
      "score": 31.0,
      "keywords": [
        "Manchester City",
        "Nottingham Forest",
        "Forest",
        "Anderson",
        "Bruyne",
        "Elliot"
      ],
      "summary": "‘They’re winners, relentless, a team I want to be part of’ Midfielder hails De Bruyne as a childhood inspiration Elliot Anderson has called Manchester City the “kings of Manchester” after completing his £116m move to the club from Nottingham Forest. The 23-year-old was a key part of England’s third-",
      "summary_cn": ""
    },
    {
      "title": "Elliot Anderson takes huge dig at Man Utd as England World Cup star reveals why he joined Man City in £116m transfer",
      "title_cn": "",
      "url": "https://www.thesun.co.uk/sport/39851813/elliot-anderson-dig-man-utd-man-city-transfer/",
      "source": "The Sun",
      "tier": 2,
      "published": "2026-07-23T16:00:00+00:00",
      "score": 31.0,
      "keywords": [
        "Nottingham Forest",
        "Man City",
        "Man Utd",
        "Forest",
        "Carrick",
        "Michael Carrick"
      ],
      "summary": "ELLIOT ANDERSON believes he is joining the ‘Kings of Manchester’ after opting for a move to City – despite interest from United. The Red Devils were tracking the England ace in recent months as Michael Carrick looked to revamp his midfield. However it became clear the former Nottingham Forest man fa",
      "summary_cn": ""
    },
    {
      "title": "Chelsea win 3-0 in secret behind-closed-doors friendly as new signing scores again and former chief’s son starts",
      "title_cn": "",
      "url": "https://www.thesun.co.uk/sport/39852622/chelsea-pre-season-bromley-friendly-behind-closed-doors-result/",
      "source": "The Sun",
      "tier": 2,
      "published": "2026-07-23T15:57:02+00:00",
      "score": 31.0,
      "keywords": [
        "Chelsea",
        "young",
        "secret",
        "behind",
        "closed",
        "doors"
      ],
      "summary": "CHELSEA continued their winning start to pre-season under Xabi Alonso as a young team won a behind-closed-doors friendly. The Blues faced League Two side Bromley and got a 3-0 victory with a host of teens involved. Joao Pedro, Jamie Gittens, and Emmanuel Emegha scored the goals. Academy defender Lan",
      "summary_cn": ""
    },
    {
      "title": "F1 considering Malaysian GP return as 2026 replacement race",
      "title_cn": "",
      "url": "https://www.skysports.com/f1/news/12040/13566259/malaysian-gp-formula-1-considering-sepang-return-to-2026-calendar-as-replacement-race-before-singapore-grand-prix",
      "source": "Sky Sports",
      "tier": 2,
      "published": "2026-07-23T18:05:00+00:00",
      "score": 25.0,
      "keywords": [
        "considering",
        "Malaysian",
        "return",
        "replacement",
        "race"
      ],
      "summary": "Formula 1 bosses are in talks with organisers of the Malaysian Grand Prix to see the Sepang race make a surprise return to the calendar this year as a stand-in event.",
      "summary_cn": ""
    },
    {
      "title": "Arsenal set to make £70m bid for Newcastle's Guimaraes",
      "title_cn": "",
      "url": "https://www.bbc.co.uk/sport/football/articles/cpq8lpj530po?at_medium=RSS&at_campaign=rss",
      "source": "BBC Sport",
      "tier": 2,
      "published": "2026-07-23T16:56:18+00:00",
      "score": 25.0,
      "keywords": [
        "Arsenal",
        "Newcastle",
        "make",
        "Guimaraes"
      ],
      "summary": "Arsenal are set to make a £70m offer for Newcastle captain Bruno Guimaraes.",
      "summary_cn": ""
    },
    {
      "title": "Arsenal ticket deals for Premier League 2026/27 season plus hospitality options to see champions at The Emirates",
      "title_cn": "",
      "url": "https://www.thesun.co.uk/sport/39227637/arsenal-premier-league-champions-ticket-hotel-packages/",
      "source": "The Sun",
      "tier": 2,
      "published": "2026-07-23T15:41:14+00:00",
      "score": 25.0,
      "keywords": [
        "Arsenal",
        "Man City",
        "ticket",
        "deals",
        "Premier",
        "League"
      ],
      "summary": "ARSENAL fans cannot wait to watch the newly-crowned Premier League champions in action again when the new season starts. The Gunners lifted the prize last season after their gripping title race with Man City. See Arsenal next season And now, following the release of the highly anticipated Premier Le",
      "summary_cn": ""
    },
    {
      "title": "Domestic abuse reports reach record UK highs during 2026 World Cup",
      "title_cn": "",
      "url": "https://www.skysports.com/football/news/12040/13566371/world-cup-2026-domestic-abuse-reports-reached-record-high-in-uk-with-major-increase-in-incidents-around-england-games",
      "source": "Sky Sports",
      "tier": 2,
      "published": "2026-07-23T16:49:00+00:00",
      "score": 20.0,
      "keywords": [
        "Domestic",
        "abuse",
        "reports",
        "reach",
        "record",
        "highs"
      ],
      "summary": "Domestic abuse reports reached record highs in the UK during the 2026 World Cup, figures have shown.",
      "summary_cn": ""
    },
    {
      "title": "Rangers confirm Dragojevic signing as seventh summer arrival",
      "title_cn": "",
      "url": "https://www.skysports.com/football/news/12040/13564373/rangers-transfer-news-vanja160dragojevic160joins-from-partizan160belgrade160as-ibrox-clubs-seventh-summer-signing",
      "source": "Sky Sports",
      "tier": 2,
      "published": "2026-07-23T17:00:00+00:00",
      "score": 20.0,
      "keywords": [
        "Rangers",
        "confirm",
        "Dragojevic",
        "signing",
        "seventh",
        "summer"
      ],
      "summary": "Rangers have signed midfielder Vanja&#160;Dragojevic on an initial four-year deal.&#160;",
      "summary_cn": ""
    },
    {
      "title": "Rangers sign 'huge potential' in Partizan captain Dragojevic",
      "title_cn": "",
      "url": "https://www.bbc.co.uk/sport/football/articles/c87ng75zlx4o?at_medium=RSS&at_campaign=rss",
      "source": "BBC Sport",
      "tier": 2,
      "published": "2026-07-23T16:13:39+00:00",
      "score": 20.0,
      "keywords": [
        "Rangers",
        "sign",
        "huge",
        "potential",
        "Partizan",
        "captain"
      ],
      "summary": "Rangers sign 20-year-old Serbia midfielder Vanja Dragojevic from Partizan for an undisclosed fee.",
      "summary_cn": ""
    },
    {
      "title": "'Motherhood should not be the end of anyone's story'",
      "title_cn": "",
      "url": "https://www.bbc.co.uk/sport/football/articles/c74g515ekyko?at_medium=RSS&at_campaign=rss",
      "source": "BBC Sport",
      "tier": 2,
      "published": "2026-07-23T17:01:46+00:00",
      "score": 20.0,
      "keywords": [
        "Motherhood",
        "anyone",
        "story"
      ],
      "summary": "After returning to football after giving birth, Nigeria's Ngozi Okobi-Okeoghene says social media users makes players \"feel bad\" about getting married and having children.",
      "summary_cn": ""
    }
  ]
}