{
  "updated_at": "2026-07-23T21:14:17.128479+00:00",
  "items": [
    {
      "title": "Defoe leaves Woking after four months in charge",
      "title_cn": "",
      "url": "https://www.bbc.co.uk/sport/football/articles/c304d47ql6jo?at_medium=RSS&at_campaign=rss",
      "source": "BBC Sport",
      "tier": 2,
      "published": "2026-07-23T21:02:11+00:00",
      "score": 31.0,
      "keywords": [
        "Tottenham",
        "Defoe",
        "Jermain Defoe",
        "leaves",
        "Woking",
        "four"
      ],
      "summary": "Former England and Tottenham striker Jermain Defoe has described his first managerial job as an \"eye-opening experience\" following his departure from National League side Woking after just four months and nine matches in charge.",
      "summary_cn": ""
    },
    {
      "title": "Arsenal and Tottenham set to go head to head for £51m-rated World Cup star, 21, who faced England",
      "title_cn": "",
      "url": "https://www.thesun.co.uk/sport/39855063/arsenal-tottenham-transfer-battle-antonio-nusa-leipzig/",
      "source": "The Sun",
      "tier": 2,
      "published": "2026-07-23T21:11:04+00:00",
      "score": 31.0,
      "keywords": [
        "Arsenal",
        "Tottenham",
        "young",
        "Antonio",
        "head",
        "rated"
      ],
      "summary": "ARSENAL and Tottenham are preparing to go head-to-head in a fierce transfer battle for RB Leipzig winger Antonio Nusa. The Norwegian international, 21, has emerged as one of the most sought-after young attackers in Europe after a stellar spell in the Bundesliga. Nusa shone at the World Cup, featurin",
      "summary_cn": ""
    },
    {
      "title": "Jermain Defoe has contract terminated just four months after England icon landed first managerial job",
      "title_cn": "",
      "url": "https://www.thesun.co.uk/sport/39855325/jermain-defoe-contract-terminated-woking/",
      "source": "The Sun",
      "tier": 2,
      "published": "2026-07-23T20:23:31+00:00",
      "score": 31.0,
      "keywords": [
        "Defoe",
        "Jermain Defoe",
        "Jermain",
        "contract",
        "terminated",
        "four"
      ],
      "summary": "JERMAIN DEFOE says he is \"really disappointed\" after his first job in management ended after only SIX competitive matches. The Premier League legend, 43, has left Woking by mutual consent just four months on from his appointment. Defoe guided the non-league minnows to a tenth place finish in the Nat",
      "summary_cn": ""
    },
    {
      "title": "Conference League clash SUSPENDED for extreme weather with players forced off pitch",
      "title_cn": "",
      "url": "https://www.thesun.co.uk/sport/39855356/conference-league-clash-suspended-extreme-weather-slovenia/",
      "source": "The Sun",
      "tier": 2,
      "published": "2026-07-23T20:23:50+00:00",
      "score": 28.0,
      "keywords": [
        "Conference",
        "League",
        "clash",
        "SUSPENDED",
        "extreme",
        "weather"
      ],
      "summary": "A EUROPA Conference League qualifier between Aluminij and Dinamo City was suspended after lightning and torrential rain forced players off the pitch in Slovenia. Reports in Slovenia confirmed the second qualifying round clash at Ljudski Vrt was halted in the 55th minute after dangerous weather swept",
      "summary_cn": ""
    },
    {
      "title": "‘Exhausted’ Erling Haaland and Wag don pyjama-style outfits as they party in millionaire’s playground Saint-Tropez",
      "title_cn": "",
      "url": "https://www.thesun.co.uk/sport/39854548/erling-haaland-wag-pyjama-party-saint-tropez/",
      "source": "The Sun",
      "tier": 2,
      "published": "2026-07-23T20:00:00+00:00",
      "score": 26.0,
      "keywords": [
        "Haaland",
        "Erling Haaland",
        "Exhausted",
        "Erling",
        "pyjama",
        "style"
      ],
      "summary": "ERLING Haaland and his Wag looked like good bedfellows in pyjama and nightie-style outfits as they partied in millionaire’s playground Saint-Tropez. The Norwegian scoring sensation has been winding down on the French Riviera with fiancee Isabel Haugseng Johansen after he bagged seven goals at the Wo",
      "summary_cn": ""
    },
    {
      "title": "Why Arsenal splashed £34m on former Norwich flop Christos Tzolis who models his game on World Cup winner",
      "title_cn": "",
      "url": "https://www.thesun.co.uk/sport/39854798/arsenal-christos-tzolis-david-villa-world-cup-mikel-arteta/",
      "source": "The Sun",
      "tier": 2,
      "published": "2026-07-23T19:39:45+00:00",
      "score": 25.0,
      "keywords": [
        "Arsenal",
        "splashed",
        "former",
        "Norwich",
        "flop",
        "Christos"
      ],
      "summary": "ARSENAL new boy Christos Tzolis models his game&nbsp; on legendary Spain forward David Villa. And the Gunners will&nbsp; hope the Greek winger can add goals to their attack after splashing out £34million to sign him on a five-year deal from Club Brugge. Tzolis, 24, flopped during a spell at Norwich ",
      "summary_cn": ""
    },
    {
      "title": "From plucky minnows to England heroes, Golden Boot showdown and Viking rows… why the 2026 World Cup was greatest ever",
      "title_cn": "",
      "url": "https://www.thesun.co.uk/sport/39854969/golden-boot-heroes-world-cup-greatest/",
      "source": "The Sun",
      "tier": 2,
      "published": "2026-07-23T20:43:25+00:00",
      "score": 20.0,
      "keywords": [
        "plucky",
        "minnows",
        "England",
        "heroes",
        "Golden",
        "Boot"
      ],
      "summary": "FIFA’S Team of Tournament features England’s Jude Bellingham, France’s Kylian Mbappe, Argentina’s Lionel Mess . . . and an unlikely hero in Cape Verde’s goalkeeper Vozinha. The veteran goalie, 40, earned special praise after pulling off a string of eye-catching saves as the minnows suffered a brutal",
      "summary_cn": ""
    }
  ]
}