{
  "updated_at": "2026-07-21T07:37:48.617745+00:00",
  "items": [
    {
      "title": "Fans baffled as English football icon pops up at the unveiling of new Prime Minister Andy Burnham",
      "title_cn": "",
      "url": "https://www.thesun.co.uk/sport/39822031/fans-baffled-peter-reid-downing-street-andy-burnham/",
      "source": "The Sun",
      "tier": 2,
      "published": "2026-07-21T07:03:12+00:00",
      "score": 31.0,
      "keywords": [
        "Downing",
        "Fans",
        "baffled",
        "English",
        "football",
        "icon"
      ],
      "summary": "FOOTBALL fans were left baffled after spotting an English football icon at the unveiling of the UK's new Prime Minister. Former Mayor of Greater Manchester Andy Burnham was sworn into office at Downing Street on Monday as he replaced Sir Keir Starmer. However, watchers were stunned to see who one of",
      "summary_cn": ""
    },
    {
      "title": "Cole Palmer’s girlfriend celebrates birthday in see-through top alongside Chelsea star following World Cup snub",
      "title_cn": "",
      "url": "https://www.thesun.co.uk/sport/39822077/cole-palmer-olivia-holder-world-cup/",
      "source": "The Sun",
      "tier": 2,
      "published": "2026-07-21T06:53:45+00:00",
      "score": 31.0,
      "keywords": [
        "Chelsea",
        "Palmer",
        "Cole",
        "girlfriend",
        "celebrates",
        "birthday"
      ],
      "summary": "OLIVIA HOLDER celebrated her birthday in a see-through top alongside Cole Palmer. The stunning blonde has been dating the Chelsea star since last year when they were spotted at Winter Wonderland together. The couple have now celebrated Olivia's 24th birthday together in an enjoyable fashion. The mod",
      "summary_cn": ""
    },
    {
      "title": "Man City auction off Pep Guardiola’s office items including historic Haaland ball, whistle and INCENSE COLLECTION",
      "title_cn": "",
      "url": "https://www.thesun.co.uk/sport/39821888/man-city-pep-guardiola-auction/",
      "source": "The Sun",
      "tier": 2,
      "published": "2026-07-21T06:19:45+00:00",
      "score": 31.0,
      "keywords": [
        "Manchester City",
        "Man City",
        "Haaland",
        "City",
        "auction",
        "Guardiola"
      ],
      "summary": "MANCHESTER CITY are auctioning off Pep Guardiola's office items following his exit from the club. The iconic manager stepped down from his position at the end of the 2025/26 Premier League season. Guardiola, 55, won everything on offer at the Cityzens during his ten-year spell. He opted to leave his",
      "summary_cn": ""
    },
    {
      "title": "Introducing football to the country with one pitch",
      "title_cn": "",
      "url": "https://www.bbc.co.uk/sport/football/articles/c5y03dermmeo?at_medium=RSS&at_campaign=rss",
      "source": "BBC Sport",
      "tier": 2,
      "published": "2026-07-21T05:47:13+00:00",
      "score": 28.0,
      "keywords": [
        "Introducing",
        "football",
        "country",
        "pitch"
      ],
      "summary": "Nauru is the only nation to have never played an official international football match and hardly anyone there plays the game. Is that about to change?",
      "summary_cn": ""
    },
    {
      "title": "Arsenal, Chelsea and Man Utd target Scott rejects new Bournemouth contract",
      "title_cn": "",
      "url": "https://www.skysports.com/football/news/12040/13565480/alex-scott-bournemouth-midfielder-rejects-new-contract-amid-strong-interest-from-arsenal-chelsea-and-manchester-united",
      "source": "Sky Sports",
      "tier": 2,
      "published": "2026-07-21T08:00:00+00:00",
      "score": 25.0,
      "keywords": [
        "Arsenal",
        "Chelsea",
        "Manchester United",
        "Bournemouth",
        "Man Utd",
        "target"
      ],
      "summary": "Alex Scott has turned down a new Bournemouth contract amid strong interest from Arsenal, Chelsea and Manchester United,&#160; Sky Sports News &#160;understands.",
      "summary_cn": ""
    },
    {
      "title": "Who am I? Guess Premier League star No 1",
      "title_cn": "",
      "url": "https://www.bbc.co.uk/sport/football/articles/clyjly9484go?at_medium=RSS&at_campaign=rss",
      "source": "BBC Sport",
      "tier": 2,
      "published": "2026-07-21T06:00:13+00:00",
      "score": 25.0,
      "keywords": [
        "Guess",
        "Premier",
        "League",
        "star"
      ],
      "summary": "Work out the identity of today's player in as few attempts as possible.",
      "summary_cn": ""
    },
    {
      "title": "Ipswich open talks for Celtic star Maeda - gossip",
      "title_cn": "",
      "url": "https://www.bbc.co.uk/sport/football/articles/clyq2w24veko?at_medium=RSS&at_campaign=rss",
      "source": "BBC Sport",
      "tier": 2,
      "published": "2026-07-21T06:45:40+00:00",
      "score": 25.0,
      "keywords": [
        "Ipswich",
        "open",
        "talks",
        "Celtic",
        "star",
        "Maeda"
      ],
      "summary": "Newly-promoted Premier League side keen on Celtic forward, with Scottish champions lining up Egypt winger as a possible replacement.",
      "summary_cn": ""
    },
    {
      "title": "World Cup fan lands date with adult star who went viral for going naked at Arsenal matches",
      "title_cn": "",
      "url": "https://www.thesun.co.uk/sport/39822043/world-cup-fan-arabella-mia-arsenal-body-paint/",
      "source": "The Sun",
      "tier": 2,
      "published": "2026-07-21T06:58:23+00:00",
      "score": 25.0,
      "keywords": [
        "Arsenal",
        "World",
        "lands",
        "date",
        "adult",
        "star"
      ],
      "summary": "ONE England fan at the World Cup went on multiple dates with Arsenal's self-proclaimed biggest female fan. Life-long Gunners fan Arabella Mia, who has gone viral on numerous occasions for her lack of outfits at the Emirates, revealed she spontaneously dated a fan while at the World Cup this summer. ",
      "summary_cn": ""
    },
    {
      "title": "The 58 transfers to watch now the World Cup is over",
      "title_cn": "",
      "url": "https://www.skysports.com/football/news/12040/13565342/transfer-news-the-players-who-could-move-before-deadline-day-now-the-world-cup-is-over",
      "source": "Sky Sports",
      "tier": 2,
      "published": "2026-07-21T08:00:00+00:00",
      "score": 20.0,
      "keywords": [
        "transfers",
        "watch",
        "World"
      ],
      "summary": "The World Cup is over but there are still more than six weeks to go in the transfer window. Here are 58 players to keep an eye on for the rest of the summer.",
      "summary_cn": ""
    },
    {
      "title": "Why World Cup can be game-changer for ambitious MLS",
      "title_cn": "",
      "url": "https://www.bbc.co.uk/sport/football/articles/c1418rm5p10o?at_medium=RSS&at_campaign=rss",
      "source": "BBC Sport",
      "tier": 2,
      "published": "2026-07-21T06:55:11+00:00",
      "score": 20.0,
      "keywords": [
        "World",
        "game",
        "changer",
        "ambitious"
      ],
      "summary": "Can the success of the 2026 World Cup help MLS become one of the world's elite leagues?",
      "summary_cn": ""
    },
    {
      "title": "Football Daily",
      "title_cn": "",
      "url": "https://www.bbc.co.uk/sounds/play/p0nzxcxt?at_medium=RSS&at_campaign=rss",
      "source": "BBC Sport",
      "tier": 2,
      "published": "2026-07-21T06:01:00+00:00",
      "score": 20.0,
      "keywords": [
        "Football",
        "Daily"
      ],
      "summary": "Spain succeed, Argentina played the villains and is the pressure off Thomas Tuchel?",
      "summary_cn": ""
    },
    {
      "title": "Could Infantino really push through a 64-team World Cup?",
      "title_cn": "",
      "url": "https://www.bbc.co.uk/sport/football/articles/cly7ley50g9o?at_medium=RSS&at_campaign=rss",
      "source": "BBC Sport",
      "tier": 2,
      "published": "2026-07-21T07:25:11+00:00",
      "score": 20.0,
      "keywords": [
        "Infantino",
        "really",
        "push",
        "through",
        "team",
        "World"
      ],
      "summary": "If we have learned one thing from Gianni Infantino's Fifa tenure, it is that more is better. That could mean 64 teams at the World Cup.",
      "summary_cn": ""
    },
    {
      "title": "World Cup 2026 in 90 seconds: a photo animation",
      "title_cn": "",
      "url": "https://www.theguardian.com/football/video/2026/jul/21/world-cup-2026-in-90-seconds-a-photo-animation",
      "source": "The Guardian",
      "tier": 2,
      "published": "2026-07-21T07:00:04+00:00",
      "score": 20.0,
      "keywords": [
        "World",
        "seconds",
        "photo",
        "animation"
      ],
      "summary": "Picture editor Jonny Weeks has created a rapid audio-visual review of the tournament featuring key moments, colourful fans ... and the precious trophy. This video contains flashing images and an audio track. Continue reading...",
      "summary_cn": ""
    },
    {
      "title": "Gaza celebrates World Cup victory of Spanish team they took into their hearts",
      "title_cn": "",
      "url": "https://www.theguardian.com/football/2026/jul/21/gaza-celebrates-world-cup-victory-of-spanish-team-they-took-into-their-hearts",
      "source": "The Guardian",
      "tier": 2,
      "published": "2026-07-21T06:00:04+00:00",
      "score": 20.0,
      "keywords": [
        "Gaza",
        "celebrates",
        "World",
        "victory",
        "Spanish",
        "team"
      ],
      "summary": "People gather at cafes and outdoor screenings to support team after Spain’s backing for Palestinian rights The Spanish football team’s World Cup win has been celebrated in the streets of Gaza, where Spain’s support for Palestinian rights and Israel’s backing for the Argentinian team turned the compe",
      "summary_cn": ""
    },
    {
      "title": "Neuer to Neymar: 11 World Cup players who retired from international football",
      "title_cn": "",
      "url": "https://www.theguardian.com/football/2026/jul/21/neuer-to-neymar-11-world-cup-players-who-retired-from-international-football",
      "source": "The Guardian",
      "tier": 2,
      "published": "2026-07-21T07:00:04+00:00",
      "score": 20.0,
      "keywords": [
        "Neuer",
        "Neymar",
        "World",
        "players",
        "retired",
        "international"
      ],
      "summary": "Germany’s 2014 World Cup winning goalkeeper and a Brazilian icon are among those who have have called time after the 2026 tournament First participated in the World Cup in 2010 before winning the trophy four years later. Germany have had little success since and their penalty shootout defeat by Para",
      "summary_cn": ""
    },
    {
      "title": "The big World Cup 2026 quiz",
      "title_cn": "",
      "url": "https://www.theguardian.com/football/2026/jul/21/the-big-world-cup-2026-quiz",
      "source": "The Guardian",
      "tier": 2,
      "published": "2026-07-21T07:00:04+00:00",
      "score": 20.0,
      "keywords": [
        "World",
        "quiz"
      ],
      "summary": "Did you catch the little details as 48 teams played 104 matches in 16 cities across 39 days? Continue reading...",
      "summary_cn": ""
    }
  ]
}