{
  "updated_at": "2026-07-08T00:06:01.190712+00:00",
  "items": [
    {
      "title": "Fulham appoint Arbeloa as Silva's successor",
      "title_cn": "",
      "url": "https://www.bbc.co.uk/sport/football/articles/cvgjnlj0d1go?at_medium=RSS&at_campaign=rss",
      "source": "BBC Sport",
      "tier": 2,
      "published": "2026-07-07T23:04:42+00:00",
      "score": 31.0,
      "keywords": [
        "Fulham",
        "Silva",
        "appoint",
        "Arbeloa",
        "successor"
      ],
      "summary": "Fulham appoint Alvaro Arbeloa as their new manager on a three-year contract, succeeding Marco Silva who left for Benfica.",
      "summary_cn": ""
    },
    {
      "title": "Marc Guehi can’t wait to face Erling Haaland in World Cup as England star says ‘no one can stop us’",
      "title_cn": "",
      "url": "https://www.thesun.co.uk/sport/39684722/erling-haaland-manchester-city-england-norway-world-cup-guehi/",
      "source": "The Sun",
      "tier": 2,
      "published": "2026-07-07T23:40:13+00:00",
      "score": 31.0,
      "keywords": [
        "Manchester City",
        "Erling Haaland",
        "Haaland",
        "Marc",
        "Guehi",
        "wait"
      ],
      "summary": "MARC GUEHI cannot wait for a World Cup quarter-final battle with Manchester City team-mate Erling Haaland. Ahead of the meeting between England and Norway on Saturday, Guehi admitted: “It’s gonna be fun!” Red-hot Haaland has hit seven goals already at the tournament. The striker, appearing at his fi",
      "summary_cn": ""
    },
    {
      "title": "Littler out to win back-to-back titles as World Matchplay field confirmed",
      "title_cn": "",
      "url": "https://www.skysports.com/darts/news/12040/13561487/betfred-world-matchplay-luke-littler-out-to-win-back-to-back-titles-as-field-confirmed-for-1m-boosted-event",
      "source": "Sky Sports",
      "tier": 2,
      "published": "2026-07-07T22:17:00+00:00",
      "score": 28.0,
      "keywords": [
        "Littler",
        "back",
        "titles",
        "World",
        "Matchplay",
        "field"
      ],
      "summary": "Luke Littler will be out to defend his Betfred World Matchplay title later this month as the world champion headlines a star-studded field heading to the Winter Gardens in Blackpool for this year's tournament, live on Sky Sports.",
      "summary_cn": ""
    },
    {
      "title": "Brazil flight home after disastrous World Cup campaign leaves with just ONE player on board",
      "title_cn": "",
      "url": "https://www.thesun.co.uk/sport/39684644/brazil-flight-home-world-cup-danilo-norway/",
      "source": "The Sun",
      "tier": 2,
      "published": "2026-07-07T23:44:23+00:00",
      "score": 26.0,
      "keywords": [
        "harte",
        "Brazil",
        "flight",
        "home",
        "disastrous",
        "World"
      ],
      "summary": "IT was a lonely trek home for one Brazil star as he was the ONLY player aboard the team's flight back from the World Cup. The Brazilian FA laid on a long-haul charter flight from New Jersey, where the Selecao were stunned by Norway on Sunday, back to Rio de Janeiro. And according to reports...",
      "summary_cn": ""
    },
    {
      "title": "Arbeloa appointed new Fulham boss",
      "title_cn": "",
      "url": "https://www.skysports.com/football/news/12040/13553985/alvaro-arbeloa-fulham-appoint-ex-real-madrid-boss-as-new-head-coach-following-marco-silvas-departure",
      "source": "Sky Sports",
      "tier": 2,
      "published": "2026-07-08T00:02:00+00:00",
      "score": 25.0,
      "keywords": [
        "Fulham",
        "Arbeloa",
        "appointed",
        "boss"
      ],
      "summary": "Alvaro Arbeloa has been appointed as Fulham's new head coach.",
      "summary_cn": ""
    },
    {
      "title": "Deloitte review: Premier League clubs’ pre-tax losses surge by 600% to £948m",
      "title_cn": "",
      "url": "https://www.theguardian.com/football/2026/jul/08/premier-league-clubs-pre-tax-losses-2024-25-deloitte-annual-review-football-finance",
      "source": "The Guardian",
      "tier": 2,
      "published": "2026-07-07T23:01:13+00:00",
      "score": 25.0,
      "keywords": [
        "Deloitte",
        "review",
        "Premier",
        "League",
        "clubs",
        "losses"
      ],
      "summary": "Losses increase between 2023-24 and 2024-25 seasons Transfer spend and lack of one-off sales account for rise The combined pre-tax losses of Premier League clubs climbed from £135m in the 2023-24 season to £948m in 2024-25, according to Deloitte’s annual review of football finance. This rise was att",
      "summary_cn": ""
    },
    {
      "title": "Switzerland break Colombian hearts with first shoot-out success",
      "title_cn": "",
      "url": "https://www.skysports.com/football/switzerland-vs-colombia/report/549860",
      "source": "Sky Sports",
      "tier": 2,
      "published": "2026-07-07T23:59:00+00:00",
      "score": 20.0,
      "keywords": [
        "Switzerland",
        "break",
        "Colombian",
        "hearts",
        "first",
        "shoot"
      ],
      "summary": "Switzerland held their nerve to edge a tight and cagey contest with a 4-3 penalty shoot-out success over unfortunate Colombia and seal a quarter-final meeting with World Cup holders Argentina on Saturday.",
      "summary_cn": ""
    },
    {
      "title": "Switzerland knock out Colombia on penalties to reach World Cup quarter-finals",
      "title_cn": "",
      "url": "https://www.theguardian.com/football/2026/jul/08/switzerland-colombia-world-cup-2026-last-16-match-report",
      "source": "The Guardian",
      "tier": 2,
      "published": "2026-07-07T23:06:57+00:00",
      "score": 20.0,
      "keywords": [
        "Switzerland",
        "knock",
        "Colombia",
        "penalties",
        "reach",
        "World"
      ],
      "summary": "Davinson Sánchez looked to the heavens. Cucho Hernández trudged back to his teammates. And by the end, the rest of the Colombian team were on the grass as Switzerland danced, nearly alone in a sea of yellow. Switzerland had prevailed on penalties, 4-3, bringing an emotional end to more than two hour",
      "summary_cn": ""
    },
    {
      "title": "Switzerland 0 Colombia 0 (4-3 pens): Swiss come through World Cup snoozefest on penalties to set up Argentina clash",
      "title_cn": "",
      "url": "https://www.thesun.co.uk/sport/39683229/switzerland-colombia-world-cup-penalties-argentina/",
      "source": "The Sun",
      "tier": 2,
      "published": "2026-07-07T22:59:37+00:00",
      "score": 20.0,
      "keywords": [
        "Switzerland",
        "Colombia",
        "pens",
        "Swiss",
        "come",
        "through"
      ],
      "summary": "SWITZERLAND won on penalties to set up a Kansas City quarter-final against the holders. Argentina’s Lionel Messi-inspired 3-2 comeback win over Egypt hours earlier was jam-packed with high drama but this was the complete opposite. But after 120 goalless minutes, Ruben Vargas clinched it 4-3 in the s",
      "summary_cn": ""
    },
    {
      "title": "‘I was really angry’ – Lionel Messi reveals reason he burst into tears after Argentina’s World Cup win over Egypt",
      "title_cn": "",
      "url": "https://www.thesun.co.uk/sport/39684197/lionel-messi-argentina-penalty-miss-egypt-world-cup-crying/",
      "source": "The Sun",
      "tier": 2,
      "published": "2026-07-07T22:42:23+00:00",
      "score": 20.0,
      "keywords": [
        "really",
        "angry",
        "Lionel",
        "Messi",
        "reveals",
        "reason"
      ],
      "summary": "LIONEL MESSI cried after Argentina's bonkers win against Egypt - because he missed another penalty. The footie icon burst into tears at full-time after inspiring yet another remarkable result at the World Cup as his side came from 2-0 down with 11 minutes to go to win in normal time. Messi, 39, equa",
      "summary_cn": ""
    }
  ]
}