{
  "updated_at": "2026-06-07T14:13:56.811962+00:00",
  "items": [
    {
      "title": "'Big things coming! - what next for Zuffa Boxing after 'incredible' UK debut?",
      "title_cn": "",
      "url": "https://www.skysports.com/boxing/news/12040/13551618/what-next-for-zuffa-boxing-after-uk-debut-dana-white-celebrates-bournemouth-show-and-teases-big-announcements-ahead",
      "source": "Sky Sports",
      "tier": 2,
      "published": "2026-06-07T13:00:00+00:00",
      "score": 26.0,
      "keywords": [
        "Smith",
        "things",
        "coming",
        "next",
        "Zuffa",
        "Boxing"
      ],
      "summary": "Even before Chris Billam-Smith&#8217;s brutal battle with Ryan Rozicki and gruelling hometown victory, Dana White was already left 'pumped' by the early success of Zuffa Boxing&#8217;s first show on UK soil.",
      "summary_cn": ""
    },
    {
      "title": "Iran's World Cup team lands in Mexico amid US visa row",
      "title_cn": "",
      "url": "https://www.bbc.com/news/articles/c5yz3zdp3jqo?at_medium=RSS&at_campaign=rss",
      "source": "BBC Sport",
      "tier": 2,
      "published": "2026-06-07T13:24:50+00:00",
      "score": 20.0,
      "keywords": [
        "Iran",
        "World",
        "team",
        "lands",
        "Mexico",
        "amid"
      ],
      "summary": "All of Iran's group games are in the US, but players and support staff will have to fly in and out of the country on match day.",
      "summary_cn": ""
    },
    {
      "title": "How Scotland reached the World Cup - told by those who made it happen",
      "title_cn": "",
      "url": "https://www.bbc.com/sport/football/articles/ckgl75x45z5o?at_medium=RSS&at_campaign=rss",
      "source": "BBC Sport",
      "tier": 2,
      "published": "2026-06-07T13:09:49+00:00",
      "score": 20.0,
      "keywords": [
        "Scotland",
        "reached",
        "World",
        "told",
        "those",
        "made"
      ],
      "summary": "Tom English speaks to those who returned Scotland to the men's World Cup finals for the first time since 1998 about the epic win over Denmark.",
      "summary_cn": ""
    },
    {
      "title": "World Cup 2022’s ‘sexiest fan’ Ivana Knoll now making her own way as DJ and mixing it with music royalty",
      "title_cn": "",
      "url": "https://www.thesun.co.uk/sport/38131270/world-cup-sexiest-fan-ivana-knoll-dj-music-royalty/",
      "source": "The Sun",
      "tier": 2,
      "published": "2026-06-07T13:23:07+00:00",
      "score": 20.0,
      "keywords": [
        "World",
        "sexiest",
        "Ivana",
        "Knoll",
        "making",
        "mixing"
      ],
      "summary": "IVANA KNOLL has been making it as a DJ since shooting to fame at the World Cup in 2022. The Croatia superfan became one of the most recognisable faces in Qatar for her daring outfits and stunning looks. Ivana, 33, made appearances at all of Croatia's games in their run to the third-place play-off ma",
      "summary_cn": ""
    },
    {
      "title": "Switzerland’s World Cup training camp surrounded by SNAKE AREA as players and staff warned",
      "title_cn": "",
      "url": "https://www.thesun.co.uk/sport/39333187/switzerland-world-cup-training-camp-snakes/",
      "source": "The Sun",
      "tier": 2,
      "published": "2026-06-07T13:15:04+00:00",
      "score": 20.0,
      "keywords": [
        "Switzerland",
        "World",
        "training",
        "camp",
        "surrounded",
        "SNAKE"
      ],
      "summary": "SWITZERLAND'S World Cup stars are on red alert after being warned of SNAKES next to their training camp. The Swiss have jetted out to San Diego to prepare for their World Cup opener against Qatar on June 13. The team are already dealing with humid temperatures in the US as they get used to their...",
      "summary_cn": ""
    },
    {
      "title": "Dropped France star goes to Harvard University just five miles from team-mates’ World Cup base",
      "title_cn": "",
      "url": "https://www.thesun.co.uk/sport/39333196/world-cup-eduardo-camavinga-harvard-france/",
      "source": "The Sun",
      "tier": 2,
      "published": "2026-06-07T13:12:03+00:00",
      "score": 20.0,
      "keywords": [
        "Dropped",
        "France",
        "star",
        "goes",
        "Harvard",
        "University"
      ],
      "summary": "EDUARDO CAMAVINGA headed to Harvard University after missing out on France's World Cup squad... just five miles from Les Blues' training base. The Real Madrid superstar, 23, was surprisingly left out of boss Didier Deschamps' 26-man roster. Rather than sulk, Camavinga jetted across the pond to visit",
      "summary_cn": ""
    }
  ]
}